the_notebook_mcp/__init__.py
the_notebook_mcp/__version__.py
the_notebook_mcp/cli.py
the_notebook_mcp/server.py
the_notebook_mcp/core/branding.py
the_notebook_mcp/core/config.py
the_notebook_mcp/core/logging.py
the_notebook_mcp/core/notebook_ops.py
the_notebook_mcp/tools/__init__.py
the_notebook_mcp/tools/cell_tools.py
the_notebook_mcp/tools/file_tools.py
the_notebook_mcp/tools/info_tools.py
the_notebook_mcp/tools/metadata_tools.py
the_notebook_mcp/tools/output_tools.py
the_notebook_mcp/tools/tool_utils.py
the_notebook_mcp-0.9.0.dist-info/METADATA
the_notebook_mcp-0.9.0.dist-info/WHEEL
the_notebook_mcp-0.9.0.dist-info/entry_points.txt
the_notebook_mcp-0.9.0.dist-info/licenses/LICENSE
the_notebook_mcp-0.9.0.dist-info/RECORD
