Metadata-Version: 2.4
Name: the-notebook-mcp
Version: 0.9.0
Summary: Model Context Protocol (MCP) implementation for Jupyter notebooks to overcome limitation with Cursor
Project-URL: Homepage, https://github.com/svallory/the-notebook-mcp
Project-URL: Bug Tracker, https://github.com/svallory/the-notebook-mcp/issues
Project-URL: Source, https://github.com/svallory/the-notebook-mcp
Author-email: Saulo Vallory <me@saulo.engineer>
License: MIT License
License-File: LICENSE
Keywords: agent,ai,cursor,fastmcp,ipynb,jupyter,mcp,nbformat,notebook,windsurf
Classifier: Development Status :: 4 - Beta
Classifier: Framework :: Jupyter
Classifier: Intended Audience :: Developers
Classifier: Intended Audience :: Science/Research
Classifier: Intended Audience :: System Administrators
Classifier: License :: OSI Approved :: MIT License
Classifier: Operating System :: OS Independent
Classifier: Programming Language :: Python
Classifier: Programming Language :: Python :: 3
Classifier: Topic :: Scientific/Engineering
Classifier: Topic :: Scientific/Engineering :: Artificial Intelligence
Classifier: Topic :: Software Development :: Libraries :: Python Modules
Classifier: Topic :: Utilities
Classifier: Typing :: Typed
Requires-Python: >=3.10
Requires-Dist: fastmcp>=2.3.3
Requires-Dist: ipython
Requires-Dist: jupyter-core
Requires-Dist: jupyter-kernel-client>=0.6.0
Requires-Dist: jupyter-nbmodel-client>=0.11.3
Requires-Dist: loguru>=0.7.3
Requires-Dist: nbconvert>=6.0
Requires-Dist: nbformat>=5.0
Provides-Extra: dev
Requires-Dist: mypy>=1.15.0; extra == 'dev'
Requires-Dist: poethepoet>=0.34.0; extra == 'dev'
Requires-Dist: pre-commit>=4.2.0; extra == 'dev'
Requires-Dist: ruff>=0.11.9; extra == 'dev'
Provides-Extra: sse
Requires-Dist: starlette>=0.25.0; extra == 'sse'
Requires-Dist: uvicorn>=0.20.0; extra == 'sse'
Provides-Extra: test
Requires-Dist: coveralls; extra == 'test'
Requires-Dist: ipykernel>=6.29.5; extra == 'test'
Requires-Dist: jupyter-server>=2.16.0; extra == 'test'
Requires-Dist: pytest-asyncio>=0.18; extra == 'test'
Requires-Dist: pytest-cov; extra == 'test'
Requires-Dist: pytest-mock; extra == 'test'
Requires-Dist: pytest>=8.3.5; extra == 'test'
